__init__.py
main.py
js_secret_santa-1.1.2.dist-info/licenses/LICENSE
util/__init__.py
util/healthcheck.py
util/logging.py
js_secret_santa-1.1.2.dist-info/METADATA
js_secret_santa-1.1.2.dist-info/WHEEL
js_secret_santa-1.1.2.dist-info/top_level.txt
js_secret_santa-1.1.2.dist-info/RECORD
