Metadata-Version: 2.4
Name: js-secret-santa
Version: 1.1.2
Summary: null
Author-email: jnstockley <jnstockley@users.noreply.github.com>
Project-URL: Homepage, https://github.com/jnstockley/secret-santa
Project-URL: Repository, https://github.com/jnstockley/secret-santa.git
Project-URL: Issues, https://github.com/jnstockley/secret-santa/issues
Keywords: starter,template,python
Classifier: Programming Language :: Python :: 3
Requires-Python: <4.0,>=3.13
License-File: LICENSE
Requires-Dist: pandas==3.0.0
Requires-Dist: python-dotenv==1.2.1
Dynamic: license-file
